AUTHORS.rst
CONTRIBUTING.rst
HISTORY.rst
LICENSE
MANIFEST.in
README.md
setup.cfg
setup.py
UTuning/UTSearch.py
UTuning/__init__.py
UTuning/cli.py
UTuning/grid_search.py
UTuning/plots.py
UTuning/scorer.py
UTuning.egg-info/PKG-INFO
UTuning.egg-info/SOURCES.txt
UTuning.egg-info/dependency_links.txt
UTuning.egg-info/entry_points.txt
UTuning.egg-info/not-zip-safe
UTuning.egg-info/top_level.txt
docs/Makefile
docs/authors.rst
docs/conf.py
docs/contributing.rst
docs/history.rst
docs/index.rst
docs/installation.rst
docs/make.bat
docs/readme.rst
docs/usage.rst
tests/__init__.py
tests/test_UTuning.py