Metadata-Version: 2.1
Name: UTuning
Version: 0.1.3
Summary: Uncertainty Tuning (UTuning) is a package that focuses on summarizing uncertainty model performance for optimum hyperparameter tuning by using the uncertainty model goodness metric.
Home-page: https://github.com/emaldonadocruz/UTuning
Author: Eduardo Maldonado-Cruz
Author-email: emaldonadocruz@utexas.edu
License: BSD license
Keywords: UTuning
Platform: UNKNOWN
Classifier: Development Status :: 2 - Pre-Alpha
Classifier: Intended Audience :: Education
Classifier: License :: OSI Approved :: BSD License
Classifier: Natural Language :: English
Classifier: Programming Language :: Python :: 3
Classifier: Programming Language :: Python :: 3.6
Classifier: Programming Language :: Python :: 3.7
Classifier: Programming Language :: Python :: 3.8
Requires-Python: >=3.6
License-File: LICENSE
License-File: AUTHORS.rst
